chily-0.9.0.dist-info/METADATA
chily-0.9.0.dist-info/WHEEL
chily/__init__.py
chily/chily.cpython-313-powerpc64le-linux-gnu.so
chily-0.9.0.dist-info/RECORD
