Metadata-Version: 2.3
Name: chily
Version: 0.9.0
Summary: Crypto wrapper library for the Decentriq platform.
Author: "decentriq" <opensource@decentriq.ch>
Author-email: "decentriq" <opensource@decentriq.ch>
Maintainer-email: decentriq <opensource@decentriq.ch>
Requires-Python: >=3.6
